{
  "project": "fleet-e2e-toy",
  "plan_file": "PLAN.md",
  "created": "2026-05-23T01:59:00Z",
  "tasks": [
    {
      "id": 1,
      "step": "Add --version / -v flag to CLI and create tool launcher scripts",
      "type": "work",
      "status": "completed",
      "tier": "cheap",
      "commit": "feat: add CLI entry point and tool launcher scripts",
      "notes": "Added src/cli.ts supporting --version and -v, created tool and tool.cmd launcher scripts."
    },
    {
      "id": 2,
      "step": "Implement validation for empty or blank strings",
      "type": "work",
      "status": "completed",
      "tier": "cheap",
      "commit": "feat: add empty or blank argument validation (Task 2)",
      "notes": "Added validation in src/cli.ts to reject empty or whitespace-only arguments with exit code 1."
    },
    {
      "id": 3,
      "step": "Implement help command and help flags",
      "type": "work",
      "status": "completed",
      "tier": "standard",
      "commit": "feat: implement help command and help flags (Task 3)",
      "notes": "Added help command, --help, and -h flag support. Added unknown argument validation with exit code 1."
    },
    {
      "id": 4,
      "step": "Add CLI unit tests",
      "type": "work",
      "status": "completed",
      "tier": "standard",
      "commit": "test: add CLI unit tests (Task 4)",
      "notes": "Created tests/cli.test.ts to programmatically test CLI behaviors, covering version flags, help options, blank string rejection, and unknown commands."
    },
    {
      "id": 5,
      "step": "VERIFY: CLI Interface",
      "type": "verify",
      "status": "completed",
      "commit": "058d507",
      "notes": "Verified typescript compilation compiles without errors. Ran all 29 tests (including CLI test suite) and they all passed."
    }
  ]
}
